Metadata-Version: 2.4
Name: orly-mcp
Version: 0.1.3
Summary: An MCP server for the ORLY tool.
Project-URL: Homepage, https://github.com/princefishthrower/orly-mcp
Project-URL: Bug Tracker, https://github.com/princefishthrower/orly-mcp/issues
Project-URL: Repository, https://github.com/princefishthrower/orly-mcp
Author-email: Chris Frewin <hi@fullstackcraft.com>
License-File: LICENSE.txt
Classifier: License :: OSI Approved :: MIT License
Classifier: Operating System :: OS Independent
Classifier: Programming Language :: Python :: 3
Requires-Python: >=3.10
Requires-Dist: fastmcp
Requires-Dist: fonttools>=4.0.0
Requires-Dist: pillow>=11
Requires-Dist: requests>=2.28.0
